[{"Restuarant Name":"McDonald's - Boat Quay","Restaurant Cuisine":"Burger, Fast Food, Halal","Restaurant Rating":"4.2","Estimate Delivery Time":"20 mins","Restaurant Distance":"1.4 km","Promotional Offers":"Free Delivery (Min. spend S$35) with GrabUnlimited, Limited Redemptions","Restaurant Notice":"No Notice","Restaurant Image Link":null,"Promo Availability":true,"Unique ID":"SGDD04944"},{"Restuarant Name":"Burger King - Boat Quay","Restaurant Cuisine":"Burgers, Fast Food","Restaurant Rating":"3.9","Estimate Delivery Time":"30 mins","Restaurant Distance":"1.4 km","Promotional Offers":"Free Delivery (Min. spend S$30) with GrabUnlimited, Limited Redemptions","Restaurant Notice":"No Notice","Restaurant Image Link":null,"Promo Availability":true,"Unique ID":"4-C6K3LLJBMFKZCT"},{"Restuarant Name":"Maharani Table - Boat Quay","Restaurant Cuisine":"Indian, Vegetarian Friendly, Noodles","Restaurant Rating":"1","Estimate Delivery Time":"45 mins","Restaurant Distance":"1.3 km","Promotional Offers":"","Restaurant Notice":"No Notice","Restaurant Image Link":null,"Promo Availability":true,"Unique ID":"4-C6VWFCJDAJ32EJ"},{"Restuarant Name":"uMart@BoatQuay - Lorong Telok","Restaurant Cuisine":"Alcohol, Snacks, Groceries, Convenience, Drinks & Beverages","Restaurant Rating":"4.7","Estimate Delivery Time":"25 mins","Restaurant Distance":"1.4 km","Promotional Offers":"S$20.60 off Jinro Flavoured Soju Combo 10-Pack","Restaurant Notice":"No Notice","Restaurant Image Link":null,"Promo Availability":true,"Unique ID":"4-C4DUNYMVBAL2FA"},{"Restuarant Name":"Fei Po Gai - BK Eating House","Restaurant Cuisine":"Chinese, Noodles, BBQ & Grill","Restaurant Rating":"4","Estimate Delivery Time":"25 mins","Restaurant Distance":"1.2 km","Promotional Offers":"Free Delivery (Min. spend S$30) with GrabUnlimited, Limited Redemptions","Restaurant Notice":"No Notice","Restaurant Image Link":null,"Promo Availability":true,"Unique ID":"4-C6TUVKNHJ3JTT2"},{"Restuarant Name":"Eat Bar - South Bridge Road","Restaurant Cuisine":"Western, Chinese, Local & Malaysian","Restaurant Rating":"4.2","Estimate Delivery Time":"20 mins","Restaurant Distance":"1.2 km","Promotional Offers":"Free Delivery (Min. spend S$30) with GrabUnlimited, Limited Redemptions","Restaurant Notice":"No Notice","Restaurant Image Link":null,"Promo Availability":true,"Unique ID":"4-C4NBHA5KRYCYJE"},{"Restuarant Name":"SF Fruits & Juices - Fullerton Waterboat House","Restaurant Cuisine":"Healthy, Drinks & Beverages, Fresh Produce","Restaurant Rating":"4.4","Estimate Delivery Time":"70 mins","Restaurant Distance":"1.6 km","Promotional Offers":"Free Delivery (Min. spend S$30) with GrabUnlimited, Limited Redemptions","Restaurant Notice":"No Notice","Restaurant Image Link":null,"Promo Availability":true,"Unique ID":"4-C4MDVPMAFGAJUE"},{"Restuarant Name":"uBooze@BoatQuay - Lorong Telok","Restaurant Cuisine":"Alcohol, Snacks, Beer, Convenience, Drinks & Beverages","Restaurant Rating":"4.5","Estimate Delivery Time":"25 mins","Restaurant Distance":"1.4 km","Promotional Offers":"S$3.10 off Bohae Bokbunja Raspberry Wine 2-Pack","Restaurant Notice":"No Notice","Restaurant Image Link":null,"Promo Availability":true,"Unique ID":"4-C4DUNYMVAUW2NT"},{"Restuarant Name":"Wingstop - Funan","Restaurant Cuisine":"Fast Food, Fried Chicken, Western, Halal","Restaurant Rating":"4.1","Estimate Delivery Time":"30 mins","Restaurant Distance":"0.5 km","Promotional Offers":"Free Delivery (Min. spend S$50) with GrabUnlimited, Limited Redemptions","Restaurant Notice":"No Notice","Restaurant Image Link":null,"Promo Availability":true,"Unique ID":"4-C4NBJNMVAYXZME"},{"Restuarant Name":"KOI Th\u00e9 - Funan","Restaurant Cuisine":"Bubble Tea, Coffee & Tea, Drinks & Beverages","Restaurant Rating":"4.7","Estimate Delivery Time":"30 mins","Restaurant Distance":"0.5 km","Promotional Offers":"Free Delivery (Min. spend S$25) with GrabUnlimited, Limited Redemptions","Restaurant Notice":"No Notice","Restaurant Image Link":null,"Promo Availability":true,"Unique ID":"4-C4NJGEDEE2X1TN"},{"Restuarant Name":"WOK HEY - Funan","Restaurant Cuisine":"Bento, Chinese, Local & Malaysian, Halal, Group Friendly","Restaurant Rating":"4.4","Estimate Delivery Time":"30 mins","Restaurant Distance":"0.9 km","Promotional Offers":"Free Delivery (Min. spend S$25) with GrabUnlimited, Limited Redemptions","Restaurant Notice":"No Notice","Restaurant Image Link":null,"Promo Availability":true,"Unique ID":"4-C2VKJ3U2C2JZTN"},{"Restuarant Name":"CHICHA San Chen - CIMB Plaza","Restaurant Cuisine":"Drinks & Beverages, Coffee & Tea, Bubble Tea, Group Friendly","Restaurant Rating":"4.4","Estimate Delivery Time":"30 mins","Restaurant Distance":"1.6 km","Promotional Offers":"Free Delivery (Min. spend S$35) with GrabUnlimited, Limited Redemptions","Restaurant Notice":"No Notice","Restaurant Image Link":null,"Promo Availability":true,"Unique ID":"4-C2CUKAU3SGNYTE"},{"Restuarant Name":"Stuff'd - Funan","Restaurant Cuisine":"Healthy, Salad, Mexican, Halal, Group Friendly","Restaurant Rating":"4.4","Estimate Delivery Time":"30 mins","Restaurant Distance":"0.5 km","Promotional Offers":"Free Delivery (Min. spend S$25) with GrabUnlimited, Limited Redemptions","Restaurant Notice":"No Notice","Restaurant Image Link":null,"Promo Availability":true,"Unique ID":"4-C2VKLAC2MBT2NJ"},{"Restuarant Name":"LaPasta - High Street Plaza","Restaurant Cuisine":"Italian, Pasta","Restaurant Rating":"4.7","Estimate Delivery Time":"20 mins","Restaurant Distance":"0.9 km","Promotional Offers":"Free Delivery (Min. spend S$50) with GrabUnlimited, Limited Redemptions","Restaurant Notice":"No Notice","Restaurant Image Link":null,"Promo Availability":true,"Unique ID":"4-C4BFUFV3JAMCRE"},{"Restuarant Name":"Sukiya - Funan","Restaurant Cuisine":"Japanese, Kids Friendly, Drinks & Beverages, Seafood, Halal","Restaurant Rating":"4.3","Estimate Delivery Time":"30 mins","Restaurant Distance":"0.5 km","Promotional Offers":"Free Delivery (Min. spend S$35) with GrabUnlimited, Limited Redemptions","Restaurant Notice":"No Notice","Restaurant Image Link":null,"Promo Availability":true,"Unique ID":"4-C3XTAN6WCCLJKA"},{"Restuarant Name":"Saap Saap Thai - Funan","Restaurant Cuisine":"Drinks & Beverages, Halal, Thai, Noodles, Breakfast & Brunch","Restaurant Rating":"4.4","Estimate Delivery Time":"30 mins","Restaurant Distance":"0.5 km","Promotional Offers":"Free Delivery (Min. spend S$40) with GrabUnlimited, Limited Redemptions","Restaurant Notice":"No Notice","Restaurant Image Link":null,"Promo Availability":true,"Unique ID":"4-CYWCATD3GAWTRN"},{"Restuarant Name":"Qi Ji - Funan","Restaurant Cuisine":"Chinese, Halal, Local & Malaysian, Group Friendly","Restaurant Rating":"4.6","Estimate Delivery Time":"30 mins","Restaurant Distance":"0.5 km","Promotional Offers":"Free Delivery (Min. spend S$40) with GrabUnlimited, Limited Redemptions","Restaurant Notice":"No Notice","Restaurant Image Link":null,"Promo Availability":true,"Unique ID":"4-CYWKAUBUPEDVJX"},{"Restuarant Name":"Grains & Co. - One Raffles Place","Restaurant Cuisine":"Healthy, Bento, Breakfast & Brunch, Salad","Restaurant Rating":"4.6","Estimate Delivery Time":"35 mins","Restaurant Distance":"1.6 km","Promotional Offers":"Free Delivery (Min. spend S$25) with GrabUnlimited, Limited Redemptions","Restaurant Notice":"No Notice","Restaurant Image Link":null,"Promo Availability":true,"Unique ID":"4-C4EUGJ4GTREJEJ"},{"Restuarant Name":"Smile Martabak - Funan","Restaurant Cuisine":"Indonesian, Dessert, Halal","Restaurant Rating":"4.2","Estimate Delivery Time":"30 mins","Restaurant Distance":"0.8 km","Promotional Offers":"Free Delivery (Min. spend S$40) with GrabUnlimited, Limited Redemptions","Restaurant Notice":"No Notice","Restaurant Image Link":null,"Promo Availability":true,"Unique ID":"4-C3KBLATWN8L1TN"},{"Restuarant Name":"Hot Shotz - Canton Street","Restaurant Cuisine":"Western, Snack","Restaurant Rating":"4.4","Estimate Delivery Time":"30 mins","Restaurant Distance":"1.6 km","Promotional Offers":"Free Delivery (Min. spend S$45) with GrabUnlimited, Limited Redemptions","Restaurant Notice":"No Notice","Restaurant Image Link":null,"Promo Availability":true,"Unique ID":"4-C3UHAXDTJBDEGN"},{"Restuarant Name":"LeNu Noodle Bar - Funan","Restaurant Cuisine":"Chinese, Noodles, Ramen","Restaurant Rating":"4.6","Estimate Delivery Time":"30 mins","Restaurant Distance":"0.5 km","Promotional Offers":"Free Delivery (Min. spend S$35) with GrabUnlimited, Limited Redemptions","Restaurant Notice":"No Notice","Restaurant Image Link":null,"Promo Availability":true,"Unique ID":"4-CYUTT6CDJ4ETNT"},{"Restuarant Name":"LiHO TEA - Funan","Restaurant Cuisine":"Coffee & Tea, Drinks & Beverages, Bubble Tea, Group Friendly","Restaurant Rating":"4.5","Estimate Delivery Time":"30 mins","Restaurant Distance":"0.8 km","Promotional Offers":"Free Delivery (Min. spend S$25) with GrabUnlimited, Limited Redemptions","Restaurant Notice":"No Notice","Restaurant Image Link":null,"Promo Availability":true,"Unique ID":"4-CZCBCGNXAY5ACA"},{"Restuarant Name":"Tim Hortons - One Raffles Place","Restaurant Cuisine":"Coffee & Tea","Restaurant Rating":"2.3","Estimate Delivery Time":"30 mins","Restaurant Distance":"1.6 km","Promotional Offers":"Free Delivery (Min. spend S$30) with GrabUnlimited, Limited Redemptions","Restaurant Notice":"No Notice","Restaurant Image Link":null,"Promo Availability":true,"Unique ID":"4-C6UCL22WT2D1SA"},{"Restuarant Name":"Briyani Hut - Boat Quay","Restaurant Cuisine":"Indian, Fried Chicken, Local & Malaysian","Restaurant Rating":"4.2","Estimate Delivery Time":"30 mins","Restaurant Distance":"1.3 km","Promotional Offers":"Free Delivery (Min. spend S$35) with GrabUnlimited, Limited Redemptions","Restaurant Notice":"No Notice","Restaurant Image Link":null,"Promo Availability":true,"Unique ID":"4-C32KFE3EFB31T2"},{"Restuarant Name":"Lucky Cafe - North Canal Road","Restaurant Cuisine":"Chinese, Noodles, Western, Filipino","Restaurant Rating":"4.3","Estimate Delivery Time":"25 mins","Restaurant Distance":"1.5 km","Promotional Offers":"Free Delivery (Min. spend S$35) with GrabUnlimited, Limited Redemptions","Restaurant Notice":"No Notice","Restaurant Image Link":null,"Promo Availability":true,"Unique ID":"4-CZDWARLXDBJYKE"},{"Restuarant Name":"Kebabs Faktory - Funan","Restaurant Cuisine":"Salad, Healthy, Halal, Fast Food, Group Friendly","Restaurant Rating":"4.1","Estimate Delivery Time":"30 mins","Restaurant Distance":"0.9 km","Promotional Offers":"Free Delivery (Min. spend S$30) with GrabUnlimited, Limited Redemptions","Restaurant Notice":"No Notice","Restaurant Image Link":null,"Promo Availability":true,"Unique ID":"4-CZAWBCC1SEVYEA"},{"Restuarant Name":"Omnivore - CIMB Plaza","Restaurant Cuisine":"Western, Salad, Group Friendly","Restaurant Rating":"4.5","Estimate Delivery Time":"30 mins","Restaurant Distance":"1.7 km","Promotional Offers":"Free Delivery (Min. spend S$25) with GrabUnlimited, Limited Redemptions","Restaurant Notice":"No Notice","Restaurant Image Link":null,"Promo Availability":true,"Unique ID":"4-C2X1T3VTTKAGLX"},{"Restuarant Name":"Ajumma's - Funan","Restaurant Cuisine":"Local & Malaysian, Korean","Restaurant Rating":"4.3","Estimate Delivery Time":"30 mins","Restaurant Distance":"0.9 km","Promotional Offers":"Free Delivery (Min. spend S$55) with GrabUnlimited, Limited Redemptions","Restaurant Notice":"No Notice","Restaurant Image Link":null,"Promo Availability":true,"Unique ID":"4-CZEXGY4XWGNBTE"},{"Restuarant Name":"Ha Jun Korean - CIMB Plaza","Restaurant Cuisine":"Japanese, Korean, Bento","Restaurant Rating":"4.6","Estimate Delivery Time":"30 mins","Restaurant Distance":"1.7 km","Promotional Offers":"Free Delivery (Min. spend S$25) with GrabUnlimited, Limited Redemptions","Restaurant Notice":"No Notice","Restaurant Image Link":null,"Promo Availability":true,"Unique ID":"4-C6B1MFC2T8JCV6"},{"Restuarant Name":"Mr Tandoor - Boat Quay","Restaurant Cuisine":"Indian, Biryani, Chinese cuisine, Curry","Restaurant Rating":"4.2","Estimate Delivery Time":"30 mins","Restaurant Distance":"1.4 km","Promotional Offers":"Free Delivery (Min. spend S$50) with GrabUnlimited, Limited Redemptions","Restaurant Notice":"No Notice","Restaurant Image Link":null,"Promo Availability":true,"Unique ID":"4-C32KFE3EET3HAX"},{"Restuarant Name":"Patrons\u2019 Box - One Raffles Place","Restaurant Cuisine":"Western, Middle Eastern, Dessert","Restaurant Rating":"4.4","Estimate Delivery Time":"30 mins","Restaurant Distance":"1.5 km","Promotional Offers":"Free Delivery (Min. spend S$30) with GrabUnlimited, Limited Redemptions","Restaurant Notice":"No Notice","Restaurant Image Link":null,"Promo Availability":true,"Unique ID":"4-C3LGR6M3C8EXCE"},{"Restuarant Name":"McDonald's - Boat Quay","Restaurant Cuisine":"Burger, Fast Food, Halal","Restaurant Rating":"4.2","Estimate Delivery Time":"20 mins","Restaurant Distance":"1.4 km","Promotional Offers":"Free Delivery (Min. spend S$35) with GrabUnlimited, Limited Redemptions","Restaurant Notice":"No Notice","Restaurant Image Link":null,"Promo Availability":true,"Unique ID":"SGDD04944"},{"Restuarant Name":"Burger King - Boat Quay","Restaurant Cuisine":"Burgers, Fast Food","Restaurant Rating":"3.9","Estimate Delivery Time":"30 mins","Restaurant Distance":"1.4 km","Promotional Offers":"Free Delivery (Min. spend S$30) with GrabUnlimited, Limited Redemptions","Restaurant Notice":"No Notice","Restaurant Image Link":null,"Promo Availability":true,"Unique ID":"4-C6K3LLJBMFKZCT"},{"Restuarant Name":"Maharani Table - Boat Quay","Restaurant Cuisine":"Indian, Vegetarian Friendly, Noodles","Restaurant Rating":"1","Estimate Delivery Time":"45 mins","Restaurant Distance":"1.3 km","Promotional Offers":"","Restaurant Notice":"No Notice","Restaurant Image Link":null,"Promo Availability":true,"Unique ID":"4-C6VWFCJDAJ32EJ"},{"Restuarant Name":"uMart@BoatQuay - Lorong Telok","Restaurant Cuisine":"Alcohol, Snacks, Groceries, Convenience, Drinks & Beverages","Restaurant Rating":"4.7","Estimate Delivery Time":"25 mins","Restaurant Distance":"1.4 km","Promotional Offers":"S$20.60 off Jinro Flavoured Soju Combo 10-Pack","Restaurant Notice":"No Notice","Restaurant Image Link":null,"Promo Availability":true,"Unique ID":"4-C4DUNYMVBAL2FA"},{"Restuarant Name":"Fei Po Gai - BK Eating House","Restaurant Cuisine":"Chinese, Noodles, BBQ & Grill","Restaurant Rating":"4","Estimate Delivery Time":"25 mins","Restaurant Distance":"1.2 km","Promotional Offers":"Free Delivery (Min. spend S$30) with GrabUnlimited, Limited Redemptions","Restaurant Notice":"No Notice","Restaurant Image Link":null,"Promo Availability":true,"Unique ID":"4-C6TUVKNHJ3JTT2"},{"Restuarant Name":"Eat Bar - South Bridge Road","Restaurant Cuisine":"Western, Chinese, Local & Malaysian","Restaurant Rating":"4.2","Estimate Delivery Time":"20 mins","Restaurant Distance":"1.2 km","Promotional Offers":"Free Delivery (Min. spend S$30) with GrabUnlimited, Limited Redemptions","Restaurant Notice":"No Notice","Restaurant Image Link":null,"Promo Availability":true,"Unique ID":"4-C4NBHA5KRYCYJE"},{"Restuarant Name":"SF Fruits & Juices - Fullerton Waterboat House","Restaurant Cuisine":"Healthy, Drinks & Beverages, Fresh Produce","Restaurant Rating":"4.4","Estimate Delivery Time":"70 mins","Restaurant Distance":"1.6 km","Promotional Offers":"Free Delivery (Min. spend S$30) with GrabUnlimited, Limited Redemptions","Restaurant Notice":"No Notice","Restaurant Image Link":null,"Promo Availability":true,"Unique ID":"4-C4MDVPMAFGAJUE"},{"Restuarant Name":"uBooze@BoatQuay - Lorong Telok","Restaurant Cuisine":"Alcohol, Snacks, Beer, Convenience, Drinks & Beverages","Restaurant Rating":"4.5","Estimate Delivery Time":"25 mins","Restaurant Distance":"1.4 km","Promotional Offers":"S$3.10 off Bohae Bokbunja Raspberry Wine 2-Pack","Restaurant Notice":"No Notice","Restaurant Image Link":null,"Promo Availability":true,"Unique ID":"4-C4DUNYMVAUW2NT"},{"Restuarant Name":"Wingstop - Funan","Restaurant Cuisine":"Fast Food, Fried Chicken, Western, Halal","Restaurant Rating":"4.1","Estimate Delivery Time":"30 mins","Restaurant Distance":"0.5 km","Promotional Offers":"Free Delivery (Min. spend S$50) with GrabUnlimited, Limited Redemptions","Restaurant Notice":"No Notice","Restaurant Image Link":null,"Promo Availability":true,"Unique ID":"4-C4NBJNMVAYXZME"},{"Restuarant Name":"KOI Th\u00e9 - Funan","Restaurant Cuisine":"Bubble Tea, Coffee & Tea, Drinks & Beverages","Restaurant Rating":"4.7","Estimate Delivery Time":"30 mins","Restaurant Distance":"0.5 km","Promotional Offers":"Free Delivery (Min. spend S$25) with GrabUnlimited, Limited Redemptions","Restaurant Notice":"No Notice","Restaurant Image Link":null,"Promo Availability":true,"Unique ID":"4-C4NJGEDEE2X1TN"},{"Restuarant Name":"WOK HEY - Funan","Restaurant Cuisine":"Bento, Chinese, Local & Malaysian, Halal, Group Friendly","Restaurant Rating":"4.4","Estimate Delivery Time":"30 mins","Restaurant Distance":"0.9 km","Promotional Offers":"Free Delivery (Min. spend S$25) with GrabUnlimited, Limited Redemptions","Restaurant Notice":"No Notice","Restaurant Image Link":null,"Promo Availability":true,"Unique ID":"4-C2VKJ3U2C2JZTN"},{"Restuarant Name":"CHICHA San Chen - CIMB Plaza","Restaurant Cuisine":"Drinks & Beverages, Coffee & Tea, Bubble Tea, Group Friendly","Restaurant Rating":"4.4","Estimate Delivery Time":"30 mins","Restaurant Distance":"1.6 km","Promotional Offers":"Free Delivery (Min. spend S$35) with GrabUnlimited, Limited Redemptions","Restaurant Notice":"No Notice","Restaurant Image Link":null,"Promo Availability":true,"Unique ID":"4-C2CUKAU3SGNYTE"},{"Restuarant Name":"Stuff'd - Funan","Restaurant Cuisine":"Healthy, Salad, Mexican, Halal, Group Friendly","Restaurant Rating":"4.4","Estimate Delivery Time":"30 mins","Restaurant Distance":"0.5 km","Promotional Offers":"Free Delivery (Min. spend S$25) with GrabUnlimited, Limited Redemptions","Restaurant Notice":"No Notice","Restaurant Image Link":null,"Promo Availability":true,"Unique ID":"4-C2VKLAC2MBT2NJ"},{"Restuarant Name":"LaPasta - High Street Plaza","Restaurant Cuisine":"Italian, Pasta","Restaurant Rating":"4.7","Estimate Delivery Time":"20 mins","Restaurant Distance":"0.9 km","Promotional Offers":"Free Delivery (Min. spend S$50) with GrabUnlimited, Limited Redemptions","Restaurant Notice":"No Notice","Restaurant Image Link":null,"Promo Availability":true,"Unique ID":"4-C4BFUFV3JAMCRE"},{"Restuarant Name":"Sukiya - Funan","Restaurant Cuisine":"Japanese, Kids Friendly, Drinks & Beverages, Seafood, Halal","Restaurant Rating":"4.3","Estimate Delivery Time":"30 mins","Restaurant Distance":"0.5 km","Promotional Offers":"Free Delivery (Min. spend S$35) with GrabUnlimited, Limited Redemptions","Restaurant Notice":"No Notice","Restaurant Image Link":null,"Promo Availability":true,"Unique ID":"4-C3XTAN6WCCLJKA"},{"Restuarant Name":"Saap Saap Thai - Funan","Restaurant Cuisine":"Drinks & Beverages, Halal, Thai, Noodles, Breakfast & Brunch","Restaurant Rating":"4.4","Estimate Delivery Time":"30 mins","Restaurant Distance":"0.5 km","Promotional Offers":"Free Delivery (Min. spend S$40) with GrabUnlimited, Limited Redemptions","Restaurant Notice":"No Notice","Restaurant Image Link":null,"Promo Availability":true,"Unique ID":"4-CYWCATD3GAWTRN"},{"Restuarant Name":"Qi Ji - Funan","Restaurant Cuisine":"Chinese, Halal, Local & Malaysian, Group Friendly","Restaurant Rating":"4.6","Estimate Delivery Time":"30 mins","Restaurant Distance":"0.5 km","Promotional Offers":"Free Delivery (Min. spend S$40) with GrabUnlimited, Limited Redemptions","Restaurant Notice":"No Notice","Restaurant Image Link":null,"Promo Availability":true,"Unique ID":"4-CYWKAUBUPEDVJX"},{"Restuarant Name":"Grains & Co. - One Raffles Place","Restaurant Cuisine":"Healthy, Bento, Breakfast & Brunch, Salad","Restaurant Rating":"4.6","Estimate Delivery Time":"35 mins","Restaurant Distance":"1.6 km","Promotional Offers":"Free Delivery (Min. spend S$25) with GrabUnlimited, Limited Redemptions","Restaurant Notice":"No Notice","Restaurant Image Link":null,"Promo Availability":true,"Unique ID":"4-C4EUGJ4GTREJEJ"},{"Restuarant Name":"Smile Martabak - Funan","Restaurant Cuisine":"Indonesian, Dessert, Halal","Restaurant Rating":"4.2","Estimate Delivery Time":"30 mins","Restaurant Distance":"0.8 km","Promotional Offers":"Free Delivery (Min. spend S$40) with GrabUnlimited, Limited Redemptions","Restaurant Notice":"No Notice","Restaurant Image Link":null,"Promo Availability":true,"Unique ID":"4-C3KBLATWN8L1TN"},{"Restuarant Name":"Hot Shotz - Canton Street","Restaurant Cuisine":"Western, Snack","Restaurant Rating":"4.4","Estimate Delivery Time":"30 mins","Restaurant Distance":"1.6 km","Promotional Offers":"Free Delivery (Min. spend S$45) with GrabUnlimited, Limited Redemptions","Restaurant Notice":"No Notice","Restaurant Image Link":null,"Promo Availability":true,"Unique ID":"4-C3UHAXDTJBDEGN"},{"Restuarant Name":"LeNu Noodle Bar - Funan","Restaurant Cuisine":"Chinese, Noodles, Ramen","Restaurant Rating":"4.6","Estimate Delivery Time":"30 mins","Restaurant Distance":"0.5 km","Promotional Offers":"Free Delivery (Min. spend S$35) with GrabUnlimited, Limited Redemptions","Restaurant Notice":"No Notice","Restaurant Image Link":null,"Promo Availability":true,"Unique ID":"4-CYUTT6CDJ4ETNT"},{"Restuarant Name":"LiHO TEA - Funan","Restaurant Cuisine":"Coffee & Tea, Drinks & Beverages, Bubble Tea, Group Friendly","Restaurant Rating":"4.5","Estimate Delivery Time":"30 mins","Restaurant Distance":"0.8 km","Promotional Offers":"Free Delivery (Min. spend S$25) with GrabUnlimited, Limited Redemptions","Restaurant Notice":"No Notice","Restaurant Image Link":null,"Promo Availability":true,"Unique ID":"4-CZCBCGNXAY5ACA"},{"Restuarant Name":"Tim Hortons - One Raffles Place","Restaurant Cuisine":"Coffee & Tea","Restaurant Rating":"2.3","Estimate Delivery Time":"30 mins","Restaurant Distance":"1.6 km","Promotional Offers":"Free Delivery (Min. spend S$30) with GrabUnlimited, Limited Redemptions","Restaurant Notice":"No Notice","Restaurant Image Link":null,"Promo Availability":true,"Unique ID":"4-C6UCL22WT2D1SA"},{"Restuarant Name":"Briyani Hut - Boat Quay","Restaurant Cuisine":"Indian, Fried Chicken, Local & Malaysian","Restaurant Rating":"4.2","Estimate Delivery Time":"30 mins","Restaurant Distance":"1.3 km","Promotional Offers":"Free Delivery (Min. spend S$35) with GrabUnlimited, Limited Redemptions","Restaurant Notice":"No Notice","Restaurant Image Link":null,"Promo Availability":true,"Unique ID":"4-C32KFE3EFB31T2"},{"Restuarant Name":"Lucky Cafe - North Canal Road","Restaurant Cuisine":"Chinese, Noodles, Western, Filipino","Restaurant Rating":"4.3","Estimate Delivery Time":"25 mins","Restaurant Distance":"1.5 km","Promotional Offers":"Free Delivery (Min. spend S$35) with GrabUnlimited, Limited Redemptions","Restaurant Notice":"No Notice","Restaurant Image Link":null,"Promo Availability":true,"Unique ID":"4-CZDWARLXDBJYKE"},{"Restuarant Name":"Kebabs Faktory - Funan","Restaurant Cuisine":"Salad, Healthy, Halal, Fast Food, Group Friendly","Restaurant Rating":"4.1","Estimate Delivery Time":"30 mins","Restaurant Distance":"0.9 km","Promotional Offers":"Free Delivery (Min. spend S$30) with GrabUnlimited, Limited Redemptions","Restaurant Notice":"No Notice","Restaurant Image Link":null,"Promo Availability":true,"Unique ID":"4-CZAWBCC1SEVYEA"},{"Restuarant Name":"Omnivore - CIMB Plaza","Restaurant Cuisine":"Western, Salad, Group Friendly","Restaurant Rating":"4.5","Estimate Delivery Time":"30 mins","Restaurant Distance":"1.7 km","Promotional Offers":"Free Delivery (Min. spend S$25) with GrabUnlimited, Limited Redemptions","Restaurant Notice":"No Notice","Restaurant Image Link":null,"Promo Availability":true,"Unique ID":"4-C2X1T3VTTKAGLX"},{"Restuarant Name":"Ajumma's - Funan","Restaurant Cuisine":"Local & Malaysian, Korean","Restaurant Rating":"4.3","Estimate Delivery Time":"30 mins","Restaurant Distance":"0.9 km","Promotional Offers":"Free Delivery (Min. spend S$55) with GrabUnlimited, Limited Redemptions","Restaurant Notice":"No Notice","Restaurant Image Link":null,"Promo Availability":true,"Unique ID":"4-CZEXGY4XWGNBTE"},{"Restuarant Name":"Ha Jun Korean - CIMB Plaza","Restaurant Cuisine":"Japanese, Korean, Bento","Restaurant Rating":"4.6","Estimate Delivery Time":"30 mins","Restaurant Distance":"1.7 km","Promotional Offers":"Free Delivery (Min. spend S$25) with GrabUnlimited, Limited Redemptions","Restaurant Notice":"No Notice","Restaurant Image Link":null,"Promo Availability":true,"Unique ID":"4-C6B1MFC2T8JCV6"},{"Restuarant Name":"Mr Tandoor - Boat Quay","Restaurant Cuisine":"Indian, Biryani, Chinese cuisine, Curry","Restaurant Rating":"4.2","Estimate Delivery Time":"30 mins","Restaurant Distance":"1.4 km","Promotional Offers":"Free Delivery (Min. spend S$50) with GrabUnlimited, Limited Redemptions","Restaurant Notice":"No Notice","Restaurant Image Link":null,"Promo Availability":true,"Unique ID":"4-C32KFE3EET3HAX"},{"Restuarant Name":"Patrons\u2019 Box - One Raffles Place","Restaurant Cuisine":"Western, Middle Eastern, Dessert","Restaurant Rating":"4.4","Estimate Delivery Time":"30 mins","Restaurant Distance":"1.5 km","Promotional Offers":"Free Delivery (Min. spend S$30) with GrabUnlimited, Limited Redemptions","Restaurant Notice":"No Notice","Restaurant Image Link":null,"Promo Availability":true,"Unique ID":"4-C3LGR6M3C8EXCE"},{"Restuarant Name":"McDonald's - Boat Quay","Restaurant Cuisine":"Burger, Fast Food, Halal","Restaurant Rating":"4.2","Estimate Delivery Time":"20 mins","Restaurant Distance":"1.4 km","Promotional Offers":"Free Delivery (Min. spend S$35) with GrabUnlimited, Limited Redemptions","Restaurant Notice":"No Notice","Restaurant Image Link":null,"Promo Availability":true,"Unique ID":"SGDD04944"},{"Restuarant Name":"Burger King - Boat Quay","Restaurant Cuisine":"Burgers, Fast Food","Restaurant Rating":"3.9","Estimate Delivery Time":"30 mins","Restaurant Distance":"1.4 km","Promotional Offers":"Free Delivery (Min. spend S$30) with GrabUnlimited, Limited Redemptions","Restaurant Notice":"No Notice","Restaurant Image Link":null,"Promo Availability":true,"Unique ID":"4-C6K3LLJBMFKZCT"},{"Restuarant Name":"Maharani Table - Boat Quay","Restaurant Cuisine":"Indian, Vegetarian Friendly, Noodles","Restaurant Rating":"1","Estimate Delivery Time":"45 mins","Restaurant Distance":"1.3 km","Promotional Offers":"","Restaurant Notice":"No Notice","Restaurant Image Link":null,"Promo Availability":true,"Unique ID":"4-C6VWFCJDAJ32EJ"},{"Restuarant Name":"uMart@BoatQuay - Lorong Telok","Restaurant Cuisine":"Alcohol, Snacks, Groceries, Convenience, Drinks & Beverages","Restaurant Rating":"4.7","Estimate Delivery Time":"25 mins","Restaurant Distance":"1.4 km","Promotional Offers":"S$20.60 off Jinro Flavoured Soju Combo 10-Pack","Restaurant Notice":"No Notice","Restaurant Image Link":null,"Promo Availability":true,"Unique ID":"4-C4DUNYMVBAL2FA"},{"Restuarant Name":"Fei Po Gai - BK Eating House","Restaurant Cuisine":"Chinese, Noodles, BBQ & Grill","Restaurant Rating":"4","Estimate Delivery Time":"25 mins","Restaurant Distance":"1.2 km","Promotional Offers":"Free Delivery (Min. spend S$30) with GrabUnlimited, Limited Redemptions","Restaurant Notice":"No Notice","Restaurant Image Link":null,"Promo Availability":true,"Unique ID":"4-C6TUVKNHJ3JTT2"},{"Restuarant Name":"Eat Bar - South Bridge Road","Restaurant Cuisine":"Western, Chinese, Local & Malaysian","Restaurant Rating":"4.2","Estimate Delivery Time":"20 mins","Restaurant Distance":"1.2 km","Promotional Offers":"Free Delivery (Min. spend S$30) with GrabUnlimited, Limited Redemptions","Restaurant Notice":"No Notice","Restaurant Image Link":null,"Promo Availability":true,"Unique ID":"4-C4NBHA5KRYCYJE"},{"Restuarant Name":"SF Fruits & Juices - Fullerton Waterboat House","Restaurant Cuisine":"Healthy, Drinks & Beverages, Fresh Produce","Restaurant Rating":"4.4","Estimate Delivery Time":"70 mins","Restaurant Distance":"1.6 km","Promotional Offers":"Free Delivery (Min. spend S$30) with GrabUnlimited, Limited Redemptions","Restaurant Notice":"No Notice","Restaurant Image Link":null,"Promo Availability":true,"Unique ID":"4-C4MDVPMAFGAJUE"},{"Restuarant Name":"uBooze@BoatQuay - Lorong Telok","Restaurant Cuisine":"Alcohol, Snacks, Beer, Convenience, Drinks & Beverages","Restaurant Rating":"4.5","Estimate Delivery Time":"25 mins","Restaurant Distance":"1.4 km","Promotional Offers":"S$3.10 off Bohae Bokbunja Raspberry Wine 2-Pack","Restaurant Notice":"No Notice","Restaurant Image Link":null,"Promo Availability":true,"Unique ID":"4-C4DUNYMVAUW2NT"},{"Restuarant Name":"Wingstop - Funan","Restaurant Cuisine":"Fast Food, Fried Chicken, Western, Halal","Restaurant Rating":"4.1","Estimate Delivery Time":"30 mins","Restaurant Distance":"0.5 km","Promotional Offers":"Free Delivery (Min. spend S$50) with GrabUnlimited, Limited Redemptions","Restaurant Notice":"No Notice","Restaurant Image Link":null,"Promo Availability":true,"Unique ID":"4-C4NBJNMVAYXZME"},{"Restuarant Name":"KOI Th\u00e9 - Funan","Restaurant Cuisine":"Bubble Tea, Coffee & Tea, Drinks & Beverages","Restaurant Rating":"4.7","Estimate Delivery Time":"30 mins","Restaurant Distance":"0.5 km","Promotional Offers":"Free Delivery (Min. spend S$25) with GrabUnlimited, Limited Redemptions","Restaurant Notice":"No Notice","Restaurant Image Link":null,"Promo Availability":true,"Unique ID":"4-C4NJGEDEE2X1TN"},{"Restuarant Name":"WOK HEY - Funan","Restaurant Cuisine":"Bento, Chinese, Local & Malaysian, Halal, Group Friendly","Restaurant Rating":"4.4","Estimate Delivery Time":"30 mins","Restaurant Distance":"0.9 km","Promotional Offers":"Free Delivery (Min. spend S$25) with GrabUnlimited, Limited Redemptions","Restaurant Notice":"No Notice","Restaurant Image Link":null,"Promo Availability":true,"Unique ID":"4-C2VKJ3U2C2JZTN"},{"Restuarant Name":"CHICHA San Chen - CIMB Plaza","Restaurant Cuisine":"Drinks & Beverages, Coffee & Tea, Bubble Tea, Group Friendly","Restaurant Rating":"4.4","Estimate Delivery Time":"30 mins","Restaurant Distance":"1.6 km","Promotional Offers":"Free Delivery (Min. spend S$35) with GrabUnlimited, Limited Redemptions","Restaurant Notice":"No Notice","Restaurant Image Link":null,"Promo Availability":true,"Unique ID":"4-C2CUKAU3SGNYTE"},{"Restuarant Name":"Stuff'd - Funan","Restaurant Cuisine":"Healthy, Salad, Mexican, Halal, Group Friendly","Restaurant Rating":"4.4","Estimate Delivery Time":"30 mins","Restaurant Distance":"0.5 km","Promotional Offers":"Free Delivery (Min. spend S$25) with GrabUnlimited, Limited Redemptions","Restaurant Notice":"No Notice","Restaurant Image Link":null,"Promo Availability":true,"Unique ID":"4-C2VKLAC2MBT2NJ"},{"Restuarant Name":"LaPasta - High Street Plaza","Restaurant Cuisine":"Italian, Pasta","Restaurant Rating":"4.7","Estimate Delivery Time":"20 mins","Restaurant Distance":"0.9 km","Promotional Offers":"Free Delivery (Min. spend S$50) with GrabUnlimited, Limited Redemptions","Restaurant Notice":"No Notice","Restaurant Image Link":null,"Promo Availability":true,"Unique ID":"4-C4BFUFV3JAMCRE"},{"Restuarant Name":"Sukiya - Funan","Restaurant Cuisine":"Japanese, Kids Friendly, Drinks & Beverages, Seafood, Halal","Restaurant Rating":"4.3","Estimate Delivery Time":"30 mins","Restaurant Distance":"0.5 km","Promotional Offers":"Free Delivery (Min. spend S$35) with GrabUnlimited, Limited Redemptions","Restaurant Notice":"No Notice","Restaurant Image Link":null,"Promo Availability":true,"Unique ID":"4-C3XTAN6WCCLJKA"},{"Restuarant Name":"Saap Saap Thai - Funan","Restaurant Cuisine":"Drinks & Beverages, Halal, Thai, Noodles, Breakfast & Brunch","Restaurant Rating":"4.4","Estimate Delivery Time":"30 mins","Restaurant Distance":"0.5 km","Promotional Offers":"Free Delivery (Min. spend S$40) with GrabUnlimited, Limited Redemptions","Restaurant Notice":"No Notice","Restaurant Image Link":null,"Promo Availability":true,"Unique ID":"4-CYWCATD3GAWTRN"},{"Restuarant Name":"Qi Ji - Funan","Restaurant Cuisine":"Chinese, Halal, Local & Malaysian, Group Friendly","Restaurant Rating":"4.6","Estimate Delivery Time":"30 mins","Restaurant Distance":"0.5 km","Promotional Offers":"Free Delivery (Min. spend S$40) with GrabUnlimited, Limited Redemptions","Restaurant Notice":"No Notice","Restaurant Image Link":null,"Promo Availability":true,"Unique ID":"4-CYWKAUBUPEDVJX"},{"Restuarant Name":"Grains & Co. - One Raffles Place","Restaurant Cuisine":"Healthy, Bento, Breakfast & Brunch, Salad","Restaurant Rating":"4.6","Estimate Delivery Time":"35 mins","Restaurant Distance":"1.6 km","Promotional Offers":"Free Delivery (Min. spend S$25) with GrabUnlimited, Limited Redemptions","Restaurant Notice":"No Notice","Restaurant Image Link":null,"Promo Availability":true,"Unique ID":"4-C4EUGJ4GTREJEJ"},{"Restuarant Name":"Smile Martabak - Funan","Restaurant Cuisine":"Indonesian, Dessert, Halal","Restaurant Rating":"4.2","Estimate Delivery Time":"30 mins","Restaurant Distance":"0.8 km","Promotional Offers":"Free Delivery (Min. spend S$40) with GrabUnlimited, Limited Redemptions","Restaurant Notice":"No Notice","Restaurant Image Link":null,"Promo Availability":true,"Unique ID":"4-C3KBLATWN8L1TN"},{"Restuarant Name":"Hot Shotz - Canton Street","Restaurant Cuisine":"Western, Snack","Restaurant Rating":"4.4","Estimate Delivery Time":"30 mins","Restaurant Distance":"1.6 km","Promotional Offers":"Free Delivery (Min. spend S$45) with GrabUnlimited, Limited Redemptions","Restaurant Notice":"No Notice","Restaurant Image Link":null,"Promo Availability":true,"Unique ID":"4-C3UHAXDTJBDEGN"},{"Restuarant Name":"LeNu Noodle Bar - Funan","Restaurant Cuisine":"Chinese, Noodles, Ramen","Restaurant Rating":"4.6","Estimate Delivery Time":"30 mins","Restaurant Distance":"0.5 km","Promotional Offers":"Free Delivery (Min. spend S$35) with GrabUnlimited, Limited Redemptions","Restaurant Notice":"No Notice","Restaurant Image Link":null,"Promo Availability":true,"Unique ID":"4-CYUTT6CDJ4ETNT"},{"Restuarant Name":"LiHO TEA - Funan","Restaurant Cuisine":"Coffee & Tea, Drinks & Beverages, Bubble Tea, Group Friendly","Restaurant Rating":"4.5","Estimate Delivery Time":"30 mins","Restaurant Distance":"0.8 km","Promotional Offers":"Free Delivery (Min. spend S$25) with GrabUnlimited, Limited Redemptions","Restaurant Notice":"No Notice","Restaurant Image Link":null,"Promo Availability":true,"Unique ID":"4-CZCBCGNXAY5ACA"},{"Restuarant Name":"Tim Hortons - One Raffles Place","Restaurant Cuisine":"Coffee & Tea","Restaurant Rating":"2.3","Estimate Delivery Time":"30 mins","Restaurant Distance":"1.6 km","Promotional Offers":"Free Delivery (Min. spend S$30) with GrabUnlimited, Limited Redemptions","Restaurant Notice":"No Notice","Restaurant Image Link":null,"Promo Availability":true,"Unique ID":"4-C6UCL22WT2D1SA"},{"Restuarant Name":"Briyani Hut - Boat Quay","Restaurant Cuisine":"Indian, Fried Chicken, Local & Malaysian","Restaurant Rating":"4.2","Estimate Delivery Time":"30 mins","Restaurant Distance":"1.3 km","Promotional Offers":"Free Delivery (Min. spend S$35) with GrabUnlimited, Limited Redemptions","Restaurant Notice":"No Notice","Restaurant Image Link":null,"Promo Availability":true,"Unique ID":"4-C32KFE3EFB31T2"},{"Restuarant Name":"Lucky Cafe - North Canal Road","Restaurant Cuisine":"Chinese, Noodles, Western, Filipino","Restaurant Rating":"4.3","Estimate Delivery Time":"25 mins","Restaurant Distance":"1.5 km","Promotional Offers":"Free Delivery (Min. spend S$35) with GrabUnlimited, Limited Redemptions","Restaurant Notice":"No Notice","Restaurant Image Link":null,"Promo Availability":true,"Unique ID":"4-CZDWARLXDBJYKE"},{"Restuarant Name":"Kebabs Faktory - Funan","Restaurant Cuisine":"Salad, Healthy, Halal, Fast Food, Group Friendly","Restaurant Rating":"4.1","Estimate Delivery Time":"30 mins","Restaurant Distance":"0.9 km","Promotional Offers":"Free Delivery (Min. spend S$30) with GrabUnlimited, Limited Redemptions","Restaurant Notice":"No Notice","Restaurant Image Link":null,"Promo Availability":true,"Unique ID":"4-CZAWBCC1SEVYEA"},{"Restuarant Name":"McDonald's - Boat Quay","Restaurant Cuisine":"Burger, Fast Food, Halal","Restaurant Rating":"4.2","Estimate Delivery Time":"20 mins","Restaurant Distance":"1.4 km","Promotional Offers":"Free Delivery (Min. spend S$35) with GrabUnlimited, Limited Redemptions","Restaurant Notice":"No Notice","Restaurant Image Link":null,"Promo Availability":true,"Unique ID":"SGDD04944"},{"Restuarant Name":"Burger King - Boat Quay","Restaurant Cuisine":"Burgers, Fast Food","Restaurant Rating":"3.9","Estimate Delivery Time":"30 mins","Restaurant Distance":"1.4 km","Promotional Offers":"Free Delivery (Min. spend S$30) with GrabUnlimited, Limited Redemptions","Restaurant Notice":"No Notice","Restaurant Image Link":null,"Promo Availability":true,"Unique ID":"4-C6K3LLJBMFKZCT"},{"Restuarant Name":"Maharani Table - Boat Quay","Restaurant Cuisine":"Indian, Vegetarian Friendly, Noodles","Restaurant Rating":"1","Estimate Delivery Time":"45 mins","Restaurant Distance":"1.3 km","Promotional Offers":"","Restaurant Notice":"No Notice","Restaurant Image Link":null,"Promo Availability":true,"Unique ID":"4-C6VWFCJDAJ32EJ"},{"Restuarant Name":"uMart@BoatQuay - Lorong Telok","Restaurant Cuisine":"Alcohol, Snacks, Groceries, Convenience, Drinks & Beverages","Restaurant Rating":"4.7","Estimate Delivery Time":"25 mins","Restaurant Distance":"1.4 km","Promotional Offers":"S$20.60 off Jinro Flavoured Soju Combo 10-Pack","Restaurant Notice":"No Notice","Restaurant Image Link":null,"Promo Availability":true,"Unique ID":"4-C4DUNYMVBAL2FA"},{"Restuarant Name":"Fei Po Gai - BK Eating House","Restaurant Cuisine":"Chinese, Noodles, BBQ & Grill","Restaurant Rating":"4","Estimate Delivery Time":"25 mins","Restaurant Distance":"1.2 km","Promotional Offers":"Free Delivery (Min. spend S$30) with GrabUnlimited, Limited Redemptions","Restaurant Notice":"No Notice","Restaurant Image Link":null,"Promo Availability":true,"Unique ID":"4-C6TUVKNHJ3JTT2"},{"Restuarant Name":"Eat Bar - South Bridge Road","Restaurant Cuisine":"Western, Chinese, Local & Malaysian","Restaurant Rating":"4.2","Estimate Delivery Time":"20 mins","Restaurant Distance":"1.2 km","Promotional Offers":"Free Delivery (Min. spend S$30) with GrabUnlimited, Limited Redemptions","Restaurant Notice":"No Notice","Restaurant Image Link":null,"Promo Availability":true,"Unique ID":"4-C4NBHA5KRYCYJE"},{"Restuarant Name":"SF Fruits & Juices - Fullerton Waterboat House","Restaurant Cuisine":"Healthy, Drinks & Beverages, Fresh Produce","Restaurant Rating":"4.4","Estimate Delivery Time":"70 mins","Restaurant Distance":"1.6 km","Promotional Offers":"Free Delivery (Min. spend S$30) with GrabUnlimited, Limited Redemptions","Restaurant Notice":"No Notice","Restaurant Image Link":null,"Promo Availability":true,"Unique ID":"4-C4MDVPMAFGAJUE"},{"Restuarant Name":"uBooze@BoatQuay - Lorong Telok","Restaurant Cuisine":"Alcohol, Snacks, Beer, Convenience, Drinks & Beverages","Restaurant Rating":"4.5","Estimate Delivery Time":"25 mins","Restaurant Distance":"1.4 km","Promotional Offers":"S$3.10 off Bohae Bokbunja Raspberry Wine 2-Pack","Restaurant Notice":"No Notice","Restaurant Image Link":null,"Promo Availability":true,"Unique ID":"4-C4DUNYMVAUW2NT"},{"Restuarant Name":"Wingstop - Funan","Restaurant Cuisine":"Fast Food, Fried Chicken, Western, Halal","Restaurant Rating":"4.1","Estimate Delivery Time":"30 mins","Restaurant Distance":"0.5 km","Promotional Offers":"Free Delivery (Min. spend S$50) with GrabUnlimited, Limited Redemptions","Restaurant Notice":"No Notice","Restaurant Image Link":null,"Promo Availability":true,"Unique ID":"4-C4NBJNMVAYXZME"},{"Restuarant Name":"KOI Th\u00e9 - Funan","Restaurant Cuisine":"Bubble Tea, Coffee & Tea, Drinks & Beverages","Restaurant Rating":"4.7","Estimate Delivery Time":"30 mins","Restaurant Distance":"0.5 km","Promotional Offers":"Free Delivery (Min. spend S$25) with GrabUnlimited, Limited Redemptions","Restaurant Notice":"No Notice","Restaurant Image Link":null,"Promo Availability":true,"Unique ID":"4-C4NJGEDEE2X1TN"},{"Restuarant Name":"WOK HEY - Funan","Restaurant Cuisine":"Bento, Chinese, Local & Malaysian, Halal, Group Friendly","Restaurant Rating":"4.4","Estimate Delivery Time":"30 mins","Restaurant Distance":"0.9 km","Promotional Offers":"Free Delivery (Min. spend S$25) with GrabUnlimited, Limited Redemptions","Restaurant Notice":"No Notice","Restaurant Image Link":null,"Promo Availability":true,"Unique ID":"4-C2VKJ3U2C2JZTN"},{"Restuarant Name":"CHICHA San Chen - CIMB Plaza","Restaurant Cuisine":"Drinks & Beverages, Coffee & Tea, Bubble Tea, Group Friendly","Restaurant Rating":"4.4","Estimate Delivery Time":"30 mins","Restaurant Distance":"1.6 km","Promotional Offers":"Free Delivery (Min. spend S$35) with GrabUnlimited, Limited Redemptions","Restaurant Notice":"No Notice","Restaurant Image Link":null,"Promo Availability":true,"Unique ID":"4-C2CUKAU3SGNYTE"},{"Restuarant Name":"Stuff'd - Funan","Restaurant Cuisine":"Healthy, Salad, Mexican, Halal, Group Friendly","Restaurant Rating":"4.4","Estimate Delivery Time":"30 mins","Restaurant Distance":"0.5 km","Promotional Offers":"Free Delivery (Min. spend S$25) with GrabUnlimited, Limited Redemptions","Restaurant Notice":"No Notice","Restaurant Image Link":null,"Promo Availability":true,"Unique ID":"4-C2VKLAC2MBT2NJ"},{"Restuarant Name":"LaPasta - High Street Plaza","Restaurant Cuisine":"Italian, Pasta","Restaurant Rating":"4.7","Estimate Delivery Time":"20 mins","Restaurant Distance":"0.9 km","Promotional Offers":"Free Delivery (Min. spend S$50) with GrabUnlimited, Limited Redemptions","Restaurant Notice":"No Notice","Restaurant Image Link":null,"Promo Availability":true,"Unique ID":"4-C4BFUFV3JAMCRE"},{"Restuarant Name":"Sukiya - Funan","Restaurant Cuisine":"Japanese, Kids Friendly, Drinks & Beverages, Seafood, Halal","Restaurant Rating":"4.3","Estimate Delivery Time":"30 mins","Restaurant Distance":"0.5 km","Promotional Offers":"Free Delivery (Min. spend S$35) with GrabUnlimited, Limited Redemptions","Restaurant Notice":"No Notice","Restaurant Image Link":null,"Promo Availability":true,"Unique ID":"4-C3XTAN6WCCLJKA"},{"Restuarant Name":"Saap Saap Thai - Funan","Restaurant Cuisine":"Drinks & Beverages, Halal, Thai, Noodles, Breakfast & Brunch","Restaurant Rating":"4.4","Estimate Delivery Time":"30 mins","Restaurant Distance":"0.5 km","Promotional Offers":"Free Delivery (Min. spend S$40) with GrabUnlimited, Limited Redemptions","Restaurant Notice":"No Notice","Restaurant Image Link":null,"Promo Availability":true,"Unique ID":"4-CYWCATD3GAWTRN"},{"Restuarant Name":"Qi Ji - Funan","Restaurant Cuisine":"Chinese, Halal, Local & Malaysian, Group Friendly","Restaurant Rating":"4.6","Estimate Delivery Time":"30 mins","Restaurant Distance":"0.5 km","Promotional Offers":"Free Delivery (Min. spend S$40) with GrabUnlimited, Limited Redemptions","Restaurant Notice":"No Notice","Restaurant Image Link":null,"Promo Availability":true,"Unique ID":"4-CYWKAUBUPEDVJX"},{"Restuarant Name":"Omnivore - CIMB Plaza","Restaurant Cuisine":"Western, Salad, Group Friendly","Restaurant Rating":"4.5","Estimate Delivery Time":"30 mins","Restaurant Distance":"1.7 km","Promotional Offers":"Free Delivery (Min. spend S$25) with GrabUnlimited, Limited Redemptions","Restaurant Notice":"No Notice","Restaurant Image Link":null,"Promo Availability":true,"Unique ID":"4-C2X1T3VTTKAGLX"},{"Restuarant Name":"Ajumma's - Funan","Restaurant Cuisine":"Local & Malaysian, Korean","Restaurant Rating":"4.3","Estimate Delivery Time":"30 mins","Restaurant Distance":"0.9 km","Promotional Offers":"Free Delivery (Min. spend S$55) with GrabUnlimited, Limited Redemptions","Restaurant Notice":"No Notice","Restaurant Image Link":null,"Promo Availability":true,"Unique ID":"4-CZEXGY4XWGNBTE"},{"Restuarant Name":"Ha Jun Korean - CIMB Plaza","Restaurant Cuisine":"Japanese, Korean, Bento","Restaurant Rating":"4.6","Estimate Delivery Time":"30 mins","Restaurant Distance":"1.7 km","Promotional Offers":"Free Delivery (Min. spend S$25) with GrabUnlimited, Limited Redemptions","Restaurant Notice":"No Notice","Restaurant Image Link":null,"Promo Availability":true,"Unique ID":"4-C6B1MFC2T8JCV6"},{"Restuarant Name":"Mr Tandoor - Boat Quay","Restaurant Cuisine":"Indian, Biryani, Chinese cuisine, Curry","Restaurant Rating":"4.2","Estimate Delivery Time":"30 mins","Restaurant Distance":"1.4 km","Promotional Offers":"Free Delivery (Min. spend S$50) with GrabUnlimited, Limited Redemptions","Restaurant Notice":"No Notice","Restaurant Image Link":null,"Promo Availability":true,"Unique ID":"4-C32KFE3EET3HAX"},{"Restuarant Name":"Patrons\u2019 Box - One Raffles Place","Restaurant Cuisine":"Western, Middle Eastern, Dessert","Restaurant Rating":"4.4","Estimate Delivery Time":"30 mins","Restaurant Distance":"1.5 km","Promotional Offers":"Free Delivery (Min. spend S$30) with GrabUnlimited, Limited Redemptions","Restaurant Notice":"No Notice","Restaurant Image Link":null,"Promo Availability":true,"Unique ID":"4-C3LGR6M3C8EXCE"},{"Restuarant Name":"Grains & Co. - One Raffles Place","Restaurant Cuisine":"Healthy, Bento, Breakfast & Brunch, Salad","Restaurant Rating":"4.6","Estimate Delivery Time":"35 mins","Restaurant Distance":"1.6 km","Promotional Offers":"Free Delivery (Min. spend S$25) with GrabUnlimited, Limited Redemptions","Restaurant Notice":"No Notice","Restaurant Image Link":null,"Promo Availability":true,"Unique ID":"4-C4EUGJ4GTREJEJ"},{"Restuarant Name":"Smile Martabak - Funan","Restaurant Cuisine":"Indonesian, Dessert, Halal","Restaurant Rating":"4.2","Estimate Delivery Time":"30 mins","Restaurant Distance":"0.8 km","Promotional Offers":"Free Delivery (Min. spend S$40) with GrabUnlimited, Limited Redemptions","Restaurant Notice":"No Notice","Restaurant Image Link":null,"Promo Availability":true,"Unique ID":"4-C3KBLATWN8L1TN"},{"Restuarant Name":"Hot Shotz - Canton Street","Restaurant Cuisine":"Western, Snack","Restaurant Rating":"4.4","Estimate Delivery Time":"30 mins","Restaurant Distance":"1.6 km","Promotional Offers":"Free Delivery (Min. spend S$45) with GrabUnlimited, Limited Redemptions","Restaurant Notice":"No Notice","Restaurant Image Link":null,"Promo Availability":true,"Unique ID":"4-C3UHAXDTJBDEGN"},{"Restuarant Name":"LeNu Noodle Bar - Funan","Restaurant Cuisine":"Chinese, Noodles, Ramen","Restaurant Rating":"4.6","Estimate Delivery Time":"30 mins","Restaurant Distance":"0.5 km","Promotional Offers":"Free Delivery (Min. spend S$35) with GrabUnlimited, Limited Redemptions","Restaurant Notice":"No Notice","Restaurant Image Link":null,"Promo Availability":true,"Unique ID":"4-CYUTT6CDJ4ETNT"},{"Restuarant Name":"LiHO TEA - Funan","Restaurant Cuisine":"Coffee & Tea, Drinks & Beverages, Bubble Tea, Group Friendly","Restaurant Rating":"4.5","Estimate Delivery Time":"30 mins","Restaurant Distance":"0.8 km","Promotional Offers":"Free Delivery (Min. spend S$25) with GrabUnlimited, Limited Redemptions","Restaurant Notice":"No Notice","Restaurant Image Link":null,"Promo Availability":true,"Unique ID":"4-CZCBCGNXAY5ACA"},{"Restuarant Name":"Tim Hortons - One Raffles Place","Restaurant Cuisine":"Coffee & Tea","Restaurant Rating":"2.3","Estimate Delivery Time":"30 mins","Restaurant Distance":"1.6 km","Promotional Offers":"Free Delivery (Min. spend S$30) with GrabUnlimited, Limited Redemptions","Restaurant Notice":"No Notice","Restaurant Image Link":null,"Promo Availability":true,"Unique ID":"4-C6UCL22WT2D1SA"},{"Restuarant Name":"Briyani Hut - Boat Quay","Restaurant Cuisine":"Indian, Fried Chicken, Local & Malaysian","Restaurant Rating":"4.2","Estimate Delivery Time":"30 mins","Restaurant Distance":"1.3 km","Promotional Offers":"Free Delivery (Min. spend S$35) with GrabUnlimited, Limited Redemptions","Restaurant Notice":"No Notice","Restaurant Image Link":null,"Promo Availability":true,"Unique ID":"4-C32KFE3EFB31T2"},{"Restuarant Name":"Lucky Cafe - North Canal Road","Restaurant Cuisine":"Chinese, Noodles, Western, Filipino","Restaurant Rating":"4.3","Estimate Delivery Time":"25 mins","Restaurant Distance":"1.5 km","Promotional Offers":"Free Delivery (Min. spend S$35) with GrabUnlimited, Limited Redemptions","Restaurant Notice":"No Notice","Restaurant Image Link":null,"Promo Availability":true,"Unique ID":"4-CZDWARLXDBJYKE"},{"Restuarant Name":"Kebabs Faktory - Funan","Restaurant Cuisine":"Salad, Healthy, Halal, Fast Food, Group Friendly","Restaurant Rating":"4.1","Estimate Delivery Time":"30 mins","Restaurant Distance":"0.9 km","Promotional Offers":"Free Delivery (Min. spend S$30) with GrabUnlimited, Limited Redemptions","Restaurant Notice":"No Notice","Restaurant Image Link":null,"Promo Availability":true,"Unique ID":"4-CZAWBCC1SEVYEA"},{"Restuarant Name":"Omnivore - CIMB Plaza","Restaurant Cuisine":"Western, Salad, Group Friendly","Restaurant Rating":"4.5","Estimate Delivery Time":"30 mins","Restaurant Distance":"1.7 km","Promotional Offers":"Free Delivery (Min. spend S$25) with GrabUnlimited, Limited Redemptions","Restaurant Notice":"No Notice","Restaurant Image Link":null,"Promo Availability":true,"Unique ID":"4-C2X1T3VTTKAGLX"},{"Restuarant Name":"McDonald's - Boat Quay","Restaurant Cuisine":"Burger, Fast Food, Halal","Restaurant Rating":"4.2","Estimate Delivery Time":"20 mins","Restaurant Distance":"1.4 km","Promotional Offers":"Free Delivery (Min. spend S$35) with GrabUnlimited, Limited Redemptions","Restaurant Notice":"No Notice","Restaurant Image Link":null,"Promo Availability":true,"Unique ID":"SGDD04944"},{"Restuarant Name":"Burger King - Boat Quay","Restaurant Cuisine":"Burgers, Fast Food","Restaurant Rating":"3.9","Estimate Delivery Time":"30 mins","Restaurant Distance":"1.4 km","Promotional Offers":"Free Delivery (Min. spend S$30) with GrabUnlimited, Limited Redemptions","Restaurant Notice":"No Notice","Restaurant Image Link":null,"Promo Availability":true,"Unique ID":"4-C6K3LLJBMFKZCT"},{"Restuarant Name":"Maharani Table - Boat Quay","Restaurant Cuisine":"Indian, Vegetarian Friendly, Noodles","Restaurant Rating":"1","Estimate Delivery Time":"45 mins","Restaurant Distance":"1.3 km","Promotional Offers":"","Restaurant Notice":"No Notice","Restaurant Image Link":null,"Promo Availability":true,"Unique ID":"4-C6VWFCJDAJ32EJ"},{"Restuarant Name":"Ajumma's - Funan","Restaurant Cuisine":"Local & Malaysian, Korean","Restaurant Rating":"4.3","Estimate Delivery Time":"30 mins","Restaurant Distance":"0.9 km","Promotional Offers":"Free Delivery (Min. spend S$55) with GrabUnlimited, Limited Redemptions","Restaurant Notice":"No Notice","Restaurant Image Link":null,"Promo Availability":true,"Unique ID":"4-CZEXGY4XWGNBTE"},{"Restuarant Name":"Ha Jun Korean - CIMB Plaza","Restaurant Cuisine":"Japanese, Korean, Bento","Restaurant Rating":"4.6","Estimate Delivery Time":"30 mins","Restaurant Distance":"1.7 km","Promotional Offers":"Free Delivery (Min. spend S$25) with GrabUnlimited, Limited Redemptions","Restaurant Notice":"No Notice","Restaurant Image Link":null,"Promo Availability":true,"Unique ID":"4-C6B1MFC2T8JCV6"},{"Restuarant Name":"Mr Tandoor - Boat Quay","Restaurant Cuisine":"Indian, Biryani, Chinese cuisine, Curry","Restaurant Rating":"4.2","Estimate Delivery Time":"30 mins","Restaurant Distance":"1.4 km","Promotional Offers":"Free Delivery (Min. spend S$50) with GrabUnlimited, Limited Redemptions","Restaurant Notice":"No Notice","Restaurant Image Link":null,"Promo Availability":true,"Unique ID":"4-C32KFE3EET3HAX"},{"Restuarant Name":"Patrons\u2019 Box - One Raffles Place","Restaurant Cuisine":"Western, Middle Eastern, Dessert","Restaurant Rating":"4.4","Estimate Delivery Time":"30 mins","Restaurant Distance":"1.5 km","Promotional Offers":"Free Delivery (Min. spend S$30) with GrabUnlimited, Limited Redemptions","Restaurant Notice":"No Notice","Restaurant Image Link":null,"Promo Availability":true,"Unique ID":"4-C3LGR6M3C8EXCE"},{"Restuarant Name":"uMart@BoatQuay - Lorong Telok","Restaurant Cuisine":"Alcohol, Snacks, Groceries, Convenience, Drinks & Beverages","Restaurant Rating":"4.7","Estimate Delivery Time":"25 mins","Restaurant Distance":"1.4 km","Promotional Offers":"S$20.60 off Jinro Flavoured Soju Combo 10-Pack","Restaurant Notice":"No Notice","Restaurant Image Link":null,"Promo Availability":true,"Unique ID":"4-C4DUNYMVBAL2FA"},{"Restuarant Name":"Fei Po Gai - BK Eating House","Restaurant Cuisine":"Chinese, Noodles, BBQ & Grill","Restaurant Rating":"4","Estimate Delivery Time":"25 mins","Restaurant Distance":"1.2 km","Promotional Offers":"Free Delivery (Min. spend S$30) with GrabUnlimited, Limited Redemptions","Restaurant Notice":"No Notice","Restaurant Image Link":null,"Promo Availability":true,"Unique ID":"4-C6TUVKNHJ3JTT2"},{"Restuarant Name":"Eat Bar - South Bridge Road","Restaurant Cuisine":"Western, Chinese, Local & Malaysian","Restaurant Rating":"4.2","Estimate Delivery Time":"20 mins","Restaurant Distance":"1.2 km","Promotional Offers":"Free Delivery (Min. spend S$30) with GrabUnlimited, Limited Redemptions","Restaurant Notice":"No Notice","Restaurant Image Link":null,"Promo Availability":true,"Unique ID":"4-C4NBHA5KRYCYJE"},{"Restuarant Name":"SF Fruits & Juices - Fullerton Waterboat House","Restaurant Cuisine":"Healthy, Drinks & Beverages, Fresh Produce","Restaurant Rating":"4.4","Estimate Delivery Time":"70 mins","Restaurant Distance":"1.6 km","Promotional Offers":"Free Delivery (Min. spend S$30) with GrabUnlimited, Limited Redemptions","Restaurant Notice":"No Notice","Restaurant Image Link":null,"Promo Availability":true,"Unique ID":"4-C4MDVPMAFGAJUE"},{"Restuarant Name":"uBooze@BoatQuay - Lorong Telok","Restaurant Cuisine":"Alcohol, Snacks, Beer, Convenience, Drinks & Beverages","Restaurant Rating":"4.5","Estimate Delivery Time":"25 mins","Restaurant Distance":"1.4 km","Promotional Offers":"S$3.10 off Bohae Bokbunja Raspberry Wine 2-Pack","Restaurant Notice":"No Notice","Restaurant Image Link":null,"Promo Availability":true,"Unique ID":"4-C4DUNYMVAUW2NT"},{"Restuarant Name":"Wingstop - Funan","Restaurant Cuisine":"Fast Food, Fried Chicken, Western, Halal","Restaurant Rating":"4.1","Estimate Delivery Time":"30 mins","Restaurant Distance":"0.5 km","Promotional Offers":"Free Delivery (Min. spend S$50) with GrabUnlimited, Limited Redemptions","Restaurant Notice":"No Notice","Restaurant Image Link":null,"Promo Availability":true,"Unique ID":"4-C4NBJNMVAYXZME"},{"Restuarant Name":"KOI Th\u00e9 - Funan","Restaurant Cuisine":"Bubble Tea, Coffee & Tea, Drinks & Beverages","Restaurant Rating":"4.7","Estimate Delivery Time":"30 mins","Restaurant Distance":"0.5 km","Promotional Offers":"Free Delivery (Min. spend S$25) with GrabUnlimited, Limited Redemptions","Restaurant Notice":"No Notice","Restaurant Image Link":null,"Promo Availability":true,"Unique ID":"4-C4NJGEDEE2X1TN"},{"Restuarant Name":"WOK HEY - Funan","Restaurant Cuisine":"Bento, Chinese, Local & Malaysian, Halal, Group Friendly","Restaurant Rating":"4.4","Estimate Delivery Time":"30 mins","Restaurant Distance":"0.9 km","Promotional Offers":"Free Delivery (Min. spend S$25) with GrabUnlimited, Limited Redemptions","Restaurant Notice":"No Notice","Restaurant Image Link":null,"Promo Availability":true,"Unique ID":"4-C2VKJ3U2C2JZTN"},{"Restuarant Name":"CHICHA San Chen - CIMB Plaza","Restaurant Cuisine":"Drinks & Beverages, Coffee & Tea, Bubble Tea, Group Friendly","Restaurant Rating":"4.4","Estimate Delivery Time":"30 mins","Restaurant Distance":"1.6 km","Promotional Offers":"Free Delivery (Min. spend S$35) with GrabUnlimited, Limited Redemptions","Restaurant Notice":"No Notice","Restaurant Image Link":null,"Promo Availability":true,"Unique ID":"4-C2CUKAU3SGNYTE"},{"Restuarant Name":"Stuff'd - Funan","Restaurant Cuisine":"Healthy, Salad, Mexican, Halal, Group Friendly","Restaurant Rating":"4.4","Estimate Delivery Time":"30 mins","Restaurant Distance":"0.5 km","Promotional Offers":"Free Delivery (Min. spend S$25) with GrabUnlimited, Limited Redemptions","Restaurant Notice":"No Notice","Restaurant Image Link":null,"Promo Availability":true,"Unique ID":"4-C2VKLAC2MBT2NJ"},{"Restuarant Name":"LaPasta - High Street Plaza","Restaurant Cuisine":"Italian, Pasta","Restaurant Rating":"4.7","Estimate Delivery Time":"20 mins","Restaurant Distance":"0.9 km","Promotional Offers":"Free Delivery (Min. spend S$50) with GrabUnlimited, Limited Redemptions","Restaurant Notice":"No Notice","Restaurant Image Link":null,"Promo Availability":true,"Unique ID":"4-C4BFUFV3JAMCRE"},{"Restuarant Name":"Sukiya - Funan","Restaurant Cuisine":"Japanese, Kids Friendly, Drinks & Beverages, Seafood, Halal","Restaurant Rating":"4.3","Estimate Delivery Time":"30 mins","Restaurant Distance":"0.5 km","Promotional Offers":"Free Delivery (Min. spend S$35) with GrabUnlimited, Limited Redemptions","Restaurant Notice":"No Notice","Restaurant Image Link":null,"Promo Availability":true,"Unique ID":"4-C3XTAN6WCCLJKA"},{"Restuarant Name":"Saap Saap Thai - Funan","Restaurant Cuisine":"Drinks & Beverages, Halal, Thai, Noodles, Breakfast & Brunch","Restaurant Rating":"4.4","Estimate Delivery Time":"30 mins","Restaurant Distance":"0.5 km","Promotional Offers":"Free Delivery (Min. spend S$40) with GrabUnlimited, Limited Redemptions","Restaurant Notice":"No Notice","Restaurant Image Link":null,"Promo Availability":true,"Unique ID":"4-CYWCATD3GAWTRN"},{"Restuarant Name":"Qi Ji - Funan","Restaurant Cuisine":"Chinese, Halal, Local & Malaysian, Group Friendly","Restaurant Rating":"4.6","Estimate Delivery Time":"30 mins","Restaurant Distance":"0.5 km","Promotional Offers":"Free Delivery (Min. spend S$40) with GrabUnlimited, Limited Redemptions","Restaurant Notice":"No Notice","Restaurant Image Link":null,"Promo Availability":true,"Unique ID":"4-CYWKAUBUPEDVJX"},{"Restuarant Name":"Grains & Co. - One Raffles Place","Restaurant Cuisine":"Healthy, Bento, Breakfast & Brunch, Salad","Restaurant Rating":"4.6","Estimate Delivery Time":"35 mins","Restaurant Distance":"1.6 km","Promotional Offers":"Free Delivery (Min. spend S$25) with GrabUnlimited, Limited Redemptions","Restaurant Notice":"No Notice","Restaurant Image Link":null,"Promo Availability":true,"Unique ID":"4-C4EUGJ4GTREJEJ"},{"Restuarant Name":"Smile Martabak - Funan","Restaurant Cuisine":"Indonesian, Dessert, Halal","Restaurant Rating":"4.2","Estimate Delivery Time":"30 mins","Restaurant Distance":"0.8 km","Promotional Offers":"Free Delivery (Min. spend S$40) with GrabUnlimited, Limited Redemptions","Restaurant Notice":"No Notice","Restaurant Image Link":null,"Promo Availability":true,"Unique ID":"4-C3KBLATWN8L1TN"},{"Restuarant Name":"Hot Shotz - Canton Street","Restaurant Cuisine":"Western, Snack","Restaurant Rating":"4.4","Estimate Delivery Time":"30 mins","Restaurant Distance":"1.6 km","Promotional Offers":"Free Delivery (Min. spend S$45) with GrabUnlimited, Limited Redemptions","Restaurant Notice":"No Notice","Restaurant Image Link":null,"Promo Availability":true,"Unique ID":"4-C3UHAXDTJBDEGN"},{"Restuarant Name":"LeNu Noodle Bar - Funan","Restaurant Cuisine":"Chinese, Noodles, Ramen","Restaurant Rating":"4.6","Estimate Delivery Time":"30 mins","Restaurant Distance":"0.5 km","Promotional Offers":"Free Delivery (Min. spend S$35) with GrabUnlimited, Limited Redemptions","Restaurant Notice":"No Notice","Restaurant Image Link":null,"Promo Availability":true,"Unique ID":"4-CYUTT6CDJ4ETNT"},{"Restuarant Name":"LiHO TEA - Funan","Restaurant Cuisine":"Coffee & Tea, Drinks & Beverages, Bubble Tea, Group Friendly","Restaurant Rating":"4.5","Estimate Delivery Time":"30 mins","Restaurant Distance":"0.8 km","Promotional Offers":"Free Delivery (Min. spend S$25) with GrabUnlimited, Limited Redemptions","Restaurant Notice":"No Notice","Restaurant Image Link":null,"Promo Availability":true,"Unique ID":"4-CZCBCGNXAY5ACA"},{"Restuarant Name":"Tim Hortons - One Raffles Place","Restaurant Cuisine":"Coffee & Tea","Restaurant Rating":"2.3","Estimate Delivery Time":"30 mins","Restaurant Distance":"1.6 km","Promotional Offers":"Free Delivery (Min. spend S$30) with GrabUnlimited, Limited Redemptions","Restaurant Notice":"No Notice","Restaurant Image Link":null,"Promo Availability":true,"Unique ID":"4-C6UCL22WT2D1SA"},{"Restuarant Name":"Briyani Hut - Boat Quay","Restaurant Cuisine":"Indian, Fried Chicken, Local & Malaysian","Restaurant Rating":"4.2","Estimate Delivery Time":"30 mins","Restaurant Distance":"1.3 km","Promotional Offers":"Free Delivery (Min. spend S$35) with GrabUnlimited, Limited Redemptions","Restaurant Notice":"No Notice","Restaurant Image Link":null,"Promo Availability":true,"Unique ID":"4-C32KFE3EFB31T2"},{"Restuarant Name":"Lucky Cafe - North Canal Road","Restaurant Cuisine":"Chinese, Noodles, Western, Filipino","Restaurant Rating":"4.3","Estimate Delivery Time":"25 mins","Restaurant Distance":"1.5 km","Promotional Offers":"Free Delivery (Min. spend S$35) with GrabUnlimited, Limited Redemptions","Restaurant Notice":"No Notice","Restaurant Image Link":null,"Promo Availability":true,"Unique ID":"4-CZDWARLXDBJYKE"},{"Restuarant Name":"Kebabs Faktory - Funan","Restaurant Cuisine":"Salad, Healthy, Halal, Fast Food, Group Friendly","Restaurant Rating":"4.1","Estimate Delivery Time":"30 mins","Restaurant Distance":"0.9 km","Promotional Offers":"Free Delivery (Min. spend S$30) with GrabUnlimited, Limited Redemptions","Restaurant Notice":"No Notice","Restaurant Image Link":null,"Promo Availability":true,"Unique ID":"4-CZAWBCC1SEVYEA"},{"Restuarant Name":"Omnivore - CIMB Plaza","Restaurant Cuisine":"Western, Salad, Group Friendly","Restaurant Rating":"4.5","Estimate Delivery Time":"30 mins","Restaurant Distance":"1.7 km","Promotional Offers":"Free Delivery (Min. spend S$25) with GrabUnlimited, Limited Redemptions","Restaurant Notice":"No Notice","Restaurant Image Link":null,"Promo Availability":true,"Unique ID":"4-C2X1T3VTTKAGLX"},{"Restuarant Name":"Ajumma's - Funan","Restaurant Cuisine":"Local & Malaysian, Korean","Restaurant Rating":"4.3","Estimate Delivery Time":"30 mins","Restaurant Distance":"0.9 km","Promotional Offers":"Free Delivery (Min. spend S$55) with GrabUnlimited, Limited Redemptions","Restaurant Notice":"No Notice","Restaurant Image Link":null,"Promo Availability":true,"Unique ID":"4-CZEXGY4XWGNBTE"},{"Restuarant Name":"Ha Jun Korean - CIMB Plaza","Restaurant Cuisine":"Japanese, Korean, Bento","Restaurant Rating":"4.6","Estimate Delivery Time":"30 mins","Restaurant Distance":"1.7 km","Promotional Offers":"Free Delivery (Min. spend S$25) with GrabUnlimited, Limited Redemptions","Restaurant Notice":"No Notice","Restaurant Image Link":null,"Promo Availability":true,"Unique ID":"4-C6B1MFC2T8JCV6"},{"Restuarant Name":"Mr Tandoor - Boat Quay","Restaurant Cuisine":"Indian, Biryani, Chinese cuisine, Curry","Restaurant Rating":"4.2","Estimate Delivery Time":"30 mins","Restaurant Distance":"1.4 km","Promotional Offers":"Free Delivery (Min. spend S$50) with GrabUnlimited, Limited Redemptions","Restaurant Notice":"No Notice","Restaurant Image Link":null,"Promo Availability":true,"Unique ID":"4-C32KFE3EET3HAX"},{"Restuarant Name":"Patrons\u2019 Box - One Raffles Place","Restaurant Cuisine":"Western, Middle Eastern, Dessert","Restaurant Rating":"4.4","Estimate Delivery Time":"30 mins","Restaurant Distance":"1.5 km","Promotional Offers":"Free Delivery (Min. spend S$30) with GrabUnlimited, Limited Redemptions","Restaurant Notice":"No Notice","Restaurant Image Link":null,"Promo Availability":true,"Unique ID":"4-C3LGR6M3C8EXCE"}]